kanbanz/__init__.py
kanbanz/core.py
kanbanz/log.py
kanbanz/utils.py
kanbanz-1.0.2.dist-info/METADATA
kanbanz-1.0.2.dist-info/WHEEL
kanbanz-1.0.2.dist-info/top_level.txt
kanbanz-1.0.2.dist-info/RECORD
