Metadata-Version: 2.4
Name: kanbanz
Version: 1.0.2
Summary: 相对完整版, 支持基本功能及其相关文档和测试
Requires-Python: >=3.10
Requires-Dist: canvaz>=0.1.4
Requires-Dist: grapherz>=0.1.7
Requires-Dist: llmada==1.0.3
Requires-Dist: promptlibz>=0.2.10
Requires-Dist: requests>=2.32.3
Requires-Dist: setuptools>=78.1.0
Requires-Dist: toml==0.10.2
